Yizhi_0404_project/__init__.py
Yizhi_0404_project/mongo_crud.py
Yizhi_0404_project-0.1.0.dist-info/METADATA
Yizhi_0404_project-0.1.0.dist-info/WHEEL
Yizhi_0404_project-0.1.0.dist-info/top_level.txt
Yizhi_0404_project-0.1.0.dist-info/RECORD
